flydata/__init__.py
flydata/sql.py
flydata/uri.py
flydata-0.0.1.dist-info/METADATA
flydata-0.0.1.dist-info/WHEEL
flydata-0.0.1.dist-info/top_level.txt
flydata-0.0.1.dist-info/RECORD
