Metadata-Version: 2.1
Name: flydata
Version: 0.0.1
Summary: Manipulate data and fly with it.
Author: Josiauh
Classifier: Programming Language :: Python :: 3
Classifier: License :: OSI Approved :: MIT License
Classifier: Operating System :: OS Independent
Classifier: Development Status :: 4 - Beta
Requires-Python: >=3.8
